pysolr.py
pysolr-3.8.1.dist-info/METADATA
pysolr-3.8.1.dist-info/RECORD
pysolr-3.8.1.dist-info/WHEEL
pysolr-3.8.1.dist-info/top_level.txt
