Metadata-Version: 2.1
Name: pysolr
Version: 3.8.1
Summary: Lightweight python wrapper for Apache Solr.
Home-page: https://github.com/django-haystack/pysolr/
Author: Daniel Lindsley
Author-email: daniel@toastdriven.com
License: BSD
Platform: UNKNOWN
Classifier: Development Status :: 5 - Production/Stable
Classifier: Intended Audience :: Developers
Classifier: License :: OSI Approved :: BSD License
Classifier: Operating System :: OS Independent
Classifier: Programming Language :: Python
Classifier: Topic :: Internet :: WWW/HTTP :: Indexing/Search
Classifier: Programming Language :: Python :: 2
Classifier: Programming Language :: Python :: 3
Provides-Extra: solrcloud
